[
    {
        "name": "Samuel W. Dana",
        "URL": "https://en.wikipedia.org/wiki/Samuel_W._Dana",
        "party": "Federalist",
        "type": "Senator",
        "state": "Connecticut",
        "birth_date": "February 13, 1760",
        "death_date": "July 21, 1830",
        "age_at_congress": 55,
        "age_at_death": 70,
        "sex": "male"
    },
    {
        "name": "David Daggett",
        "URL": "https://en.wikipedia.org/wiki/David_Daggett",
        "party": "Federalist",
        "type": "Senator",
        "state": "Connecticut",
        "birth_date": "December 31, 1764",
        "death_date": "April 12, 1851",
        "age_at_congress": 50,
        "age_at_death": 86,
        "sex": "male"
    },
    {
        "name": "Outerbridge Horsey",
        "URL": "https://en.wikipedia.org/wiki/Outerbridge_Horsey",
        "party": "Federalist",
        "type": "Senator",
        "state": "Delaware",
        "birth_date": "March 5, 1777",
        "death_date": "June 9, 1842",
        "age_at_congress": 38,
        "age_at_death": 65,
        "sex": "male"
    },
    {
        "name": "William H. Wells",
        "URL": "https://en.wikipedia.org/wiki/William_H._Wells",
        "party": "Federalist",
        "type": "Senator",
        "state": "Delaware",
        "birth_date": "January 7, 1769",
        "death_date": "March 11, 1829",
        "age_at_congress": 46,
        "age_at_death": 60,
        "sex": "male"
    },
    {
        "name": "William W. Bibb",
        "URL": "https://en.wikipedia.org/wiki/William_Wyatt_Bibb",
        "party": "Democratic-Republican",
        "type": "Senator",
        "state": "Georgia",
        "birth_date": "October 2, 1781",
        "death_date": "July 10, 1820",
        "age_at_congress": 33,
        "age_at_death": 38,
        "sex": "male"
    },
    {
        "name": "Charles Tait",
        "URL": "https://en.wikipedia.org/wiki/Charles_Tait_(politician)",
        "party": "Democratic-Republican",
        "type": "Senator",
        "state": "Georgia",
        "birth_date": "February 1, 1768",
        "death_date": "October 7, 1835",
        "age_at_congress": 47,
        "age_at_death": 67,
        "sex": "male"
    },
    {
        "name": "James Noble",
        "URL": "https://en.wikipedia.org/wiki/James_Noble_(senator)",
        "party": "Democratic-Republican",
        "type": "Senator",
        "state": "Indiana",
        "birth_date": "December 16, 1785",
        "death_date": "February 26, 1831",
        "age_at_congress": 29,
        "age_at_death": 45,
        "sex": "male"
    },
    {
        "name": "Waller Taylor",
        "URL": "https://en.wikipedia.org/wiki/Waller_Taylor",
        "party": "Democratic-Republican",
        "type": "Senator",
        "state": "Indiana",
        "birth_date": "January 1, 1775",
        "death_date": "August 26, 1826",
        "age_at_congress": 40,
        "age_at_death": 51,
        "sex": "male"
    },
    {
        "name": "William T. Barry",
        "URL": "https://en.wikipedia.org/wiki/William_T._Barry",
        "party": "Democratic-Republican",
        "type": "Senator",
        "state": "Kentucky",
        "birth_date": "February 5, 1784",
        "death_date": "August 30, 1835",
        "age_at_congress": 31,
        "age_at_death": 51,
        "sex": "male"
    },
    {
        "name": "Isham Talbot",
        "URL": "https://en.wikipedia.org/wiki/Isham_Talbot",
        "party": "Democratic-Republican",
        "type": "Senator",
        "state": "Kentucky",
        "birth_date": "January 1, 1773",
        "death_date": "September 25, 1837",
        "age_at_congress": 42,
        "age_at_death": 64,
        "sex": "male"
    },
    {
        "name": "James Brown",
        "URL": "https://en.wikipedia.org/wiki/James_Brown_(Senator)",
        "party": "Democratic-Republican",
        "type": "Senator",
        "state": "Louisiana",
        "birth_date": "September 11, 1766",
        "death_date": "April 7, 1835",
        "age_at_congress": 48,
        "age_at_death": 68,
        "sex": "male"
    },
    {
        "name": "Eligius Fromentin",
        "URL": "https://en.wikipedia.org/wiki/Eligius_Fromentin",
        "party": "Democratic-Republican",
        "type": "Senator",
        "state": "Louisiana",
        "birth_date": "January 1, 1767",
        "death_date": "October 6, 1822",
        "age_at_congress": 48,
        "age_at_death": 55,
        "sex": "male"
    },
    {
        "name": "Robert Goodloe Harper",
        "URL": "https://en.wikipedia.org/wiki/Robert_Goodloe_Harper",
        "party": "Federalist",
        "type": "Senator",
        "state": "Maryland",
        "birth_date": "January 1, 1765",
        "death_date": "January 14, 1825",
        "age_at_congress": 50,
        "age_at_death": 60,
        "sex": "male"
    },
    {
        "name": "Robert H. Goldsborough",
        "URL": "https://en.wikipedia.org/wiki/Robert_Henry_Goldsborough",
        "party": "Federalist",
        "type": "Senator",
        "state": "Maryland",
        "birth_date": "January 4, 1779",
        "death_date": "October 5, 1836",
        "age_at_congress": 36,
        "age_at_death": 57,
        "sex": "male"
    },
    {
        "name": "Christopher Gore",
        "URL": "https://en.wikipedia.org/wiki/Christopher_Gore",
        "party": "Federalist",
        "type": "Senator",
        "state": "Massachusetts",
        "birth_date": "September 21, 1758",
        "death_date": "March 1, 1827",
        "age_at_congress": 56,
        "age_at_death": 68,
        "sex": "male"
    },
    {
        "name": "Joseph Bradley Varnum",
        "URL": "https://en.wikipedia.org/wiki/Joseph_Bradley_Varnum",
        "party": "Democratic-Republican",
        "type": "Senator",
        "state": "Massachusetts",
        "birth_date": "January 29, 1750",
        "death_date": "September 21, 1821",
        "age_at_congress": 65,
        "age_at_death": 71,
        "sex": "male"
    },
    {
        "name": "Thomas W. Thompson",
        "URL": "https://en.wikipedia.org/wiki/Thomas_W._Thompson",
        "party": "Federalist",
        "type": "Senator",
        "state": "New Hampshire",
        "birth_date": "March 15, 1766",
        "death_date": "October 1, 1821",
        "age_at_congress": 49,
        "age_at_death": 55,
        "sex": "male"
    },
    {
        "name": "Jeremiah Mason",
        "URL": "https://en.wikipedia.org/wiki/Jeremiah_Mason",
        "party": "Federalist",
        "type": "Senator",
        "state": "New Hampshire",
        "birth_date": "April 27, 1768",
        "death_date": "October 14, 1848",
        "age_at_congress": 46,
        "age_at_death": 80,
        "sex": "male"
    },
    {
        "name": "James J. Wilson",
        "URL": "https://en.wikipedia.org/wiki/James_J._Wilson",
        "party": "Democratic-Republican",
        "type": "Senator",
        "state": "New Jersey",
        "birth_date": "January 1, 1775",
        "death_date": "July 28, 1824",
        "age_at_congress": 40,
        "age_at_death": 49,
        "sex": "male"
    },
    {
        "name": "John Condit",
        "URL": "https://en.wikipedia.org/wiki/John_Condit",
        "party": "Democratic-Republican",
        "type": "Senator",
        "state": "New Jersey",
        "birth_date": "July 8, 1755",
        "death_date": "May 4, 1834",
        "age_at_congress": 59,
        "age_at_death": 78,
        "sex": "male"
    },
    {
        "name": "Nathan Sanford",
        "URL": "https://en.wikipedia.org/wiki/Nathan_Sanford",
        "party": "Democratic-Republican",
        "type": "Senator",
        "state": "New York",
        "birth_date": "November 5, 1777",
        "death_date": "October 17, 1838",
        "age_at_congress": 37,
        "age_at_death": 60,
        "sex": "male"
    },
    {
        "name": "Rufus King",
        "URL": "https://en.wikipedia.org/wiki/Rufus_King",
        "party": "Federalist",
        "type": "Senator",
        "state": "New York",
        "birth_date": "March 24, 1755",
        "death_date": "April 29, 1827",
        "age_at_congress": 59,
        "age_at_death": 72,
        "sex": "male"
    },
    {
        "name": "James Turner",
        "URL": "https://en.wikipedia.org/wiki/James_Turner_(North_Carolina_politician)",
        "party": "Democratic-Republican",
        "type": "Senator",
        "state": "North Carolina",
        "birth_date": "December 20, 1766",
        "death_date": "January 15, 1824",
        "age_at_congress": 48,
        "age_at_death": 57,
        "sex": "male"
    },
    {
        "name": "Francis Locke Jr.",
        "URL": "https://en.wikipedia.org/wiki/Francis_Locke_Jr.",
        "party": "Democratic-Republican",
        "type": "Senator",
        "state": "North Carolina",
        "birth_date": "October 31, 1766",
        "death_date": "January 8, 1823",
        "age_at_congress": 48,
        "age_at_death": 56,
        "sex": "male"
    },
    {
        "name": "Benjamin Ruggles",
        "URL": "https://en.wikipedia.org/wiki/Benjamin_Ruggles",
        "party": "Democratic-Republican",
        "type": "Senator",
        "state": "Ohio",
        "birth_date": "February 21, 1783",
        "death_date": "September 2, 1857",
        "age_at_congress": 32,
        "age_at_death": 74,
        "sex": "male"
    },
    {
        "name": "Jeremiah Morrow",
        "URL": "https://en.wikipedia.org/wiki/Jeremiah_Morrow",
        "party": "Democratic-Republican",
        "type": "Senator",
        "state": "Ohio",
        "birth_date": "October 6, 1771",
        "death_date": "March 22, 1852",
        "age_at_congress": 43,
        "age_at_death": 80,
        "sex": "male"
    },
    {
        "name": "Jonathan Roberts",
        "URL": "https://en.wikipedia.org/wiki/Jonathan_Roberts_(politician)",
        "party": "Democratic-Republican",
        "type": "Senator",
        "state": "Pennsylvania",
        "birth_date": "August 16, 1771",
        "death_date": "July 24, 1854",
        "age_at_congress": 43,
        "age_at_death": 82,
        "sex": "male"
    },
    {
        "name": "Abner Lacock",
        "URL": "https://en.wikipedia.org/wiki/Abner_Lacock",
        "party": "Democratic-Republican",
        "type": "Senator",
        "state": "Pennsylvania",
        "birth_date": "July 9, 1770",
        "death_date": "April 12, 1837",
        "age_at_congress": 44,
        "age_at_death": 66,
        "sex": "male"
    },
    {
        "name": "William Hunter",
        "URL": "https://en.wikipedia.org/wiki/William_Hunter_(Senator)",
        "party": "Federalist",
        "type": "Senator",
        "state": "Rhode Island",
        "birth_date": "November 26, 1774",
        "death_date": "December 3, 1849",
        "age_at_congress": 40,
        "age_at_death": 75,
        "sex": "male"
    },
    {
        "name": "Jeremiah B. Howell",
        "URL": "https://en.wikipedia.org/wiki/Jeremiah_B._Howell",
        "party": "Democratic-Republican",
        "type": "Senator",
        "state": "Rhode Island",
        "birth_date": "August 28, 1771",
        "death_date": "February 5, 1822",
        "age_at_congress": 43,
        "age_at_death": 50,
        "sex": "male"
    },
    {
        "name": "John Taylor",
        "URL": "https://en.wikipedia.org/wiki/John_Taylor_(1770%E2%80%931832)",
        "party": "Democratic-Republican",
        "type": "Senator",
        "state": "South Carolina",
        "birth_date": "May 4, 1770",
        "death_date": "April 16, 1832",
        "age_at_congress": 44,
        "age_at_death": 61,
        "sex": "male"
    },
    {
        "name": "John Gaillard",
        "URL": "https://en.wikipedia.org/wiki/John_Gaillard",
        "party": "Democratic-Republican",
        "type": "Senator",
        "state": "South Carolina",
        "birth_date": "September 5, 1765",
        "death_date": "February 26, 1826",
        "age_at_congress": 49,
        "age_at_death": 60,
        "sex": "male"
    },
    {
        "name": "George W. Campbell",
        "URL": "https://en.wikipedia.org/wiki/George_W._Campbell",
        "party": "Democratic-Republican",
        "type": "Senator",
        "state": "Tennessee",
        "birth_date": "February 9, 1769",
        "death_date": "February 17, 1848",
        "age_at_congress": 46,
        "age_at_death": 79,
        "sex": "male"
    },
    {
        "name": "Jesse Wharton",
        "URL": "https://en.wikipedia.org/wiki/Jesse_Wharton",
        "party": "Democratic-Republican",
        "type": "Senator",
        "state": "Tennessee",
        "birth_date": "July 29, 1782",
        "death_date": "July 22, 1833",
        "age_at_congress": 32,
        "age_at_death": 51,
        "sex": "male"
    },
    {
        "name": "Isaac Tichenor",
        "URL": "https://en.wikipedia.org/wiki/Isaac_Tichenor",
        "party": "Federalist",
        "type": "Senator",
        "state": "Vermont",
        "birth_date": "February 8, 1754",
        "death_date": "December 11, 1838",
        "age_at_congress": 61,
        "age_at_death": 84,
        "sex": "male"
    },
    {
        "name": "Dudley Chase",
        "URL": "https://en.wikipedia.org/wiki/Dudley_Chase",
        "party": "Democratic-Republican",
        "type": "Senator",
        "state": "Vermont",
        "birth_date": "December 30, 1771",
        "death_date": "February 23, 1846",
        "age_at_congress": 43,
        "age_at_death": 74,
        "sex": "male"
    },
    {
        "name": "James Barbour",
        "URL": "https://en.wikipedia.org/wiki/James_Barbour",
        "party": "Democratic-Republican",
        "type": "Senator",
        "state": "Virginia",
        "birth_date": "June 10, 1775",
        "death_date": "June 7, 1842",
        "age_at_congress": 39,
        "age_at_death": 67,
        "sex": "male"
    },
    {
        "name": "Armistead T. Mason",
        "URL": "https://en.wikipedia.org/wiki/Armistead_Thomson_Mason",
        "party": "Democratic-Republican",
        "type": "Senator",
        "state": "Virginia",
        "birth_date": "August 4, 1787",
        "death_date": "February 6, 1819",
        "age_at_congress": 27,
        "age_at_death": 31,
        "sex": "male"
    },
    {
        "name": "Epaphroditus Champion",
        "URL": "https://en.wikipedia.org/wiki/Epaphroditus_Champion",
        "party": "Federalist",
        "type": "Representative",
        "state": "Connecticut",
        "birth_date": "April 6, 1756",
        "death_date": "December 22, 1834",
        "age_at_congress": 58,
        "age_at_death": 78,
        "sex": "male"
    },
    {
        "name": "John Davenport",
        "URL": "https://en.wikipedia.org/wiki/John_Davenport_(Connecticut)",
        "party": "Federalist",
        "type": "Representative",
        "state": "Connecticut",
        "birth_date": "January 16, 1752",
        "death_date": "November 28, 1830",
        "age_at_congress": 63,
        "age_at_death": 78,
        "sex": "male"
    },
    {
        "name": "Lyman Law",
        "URL": "https://en.wikipedia.org/wiki/Lyman_Law",
        "party": "Federalist",
        "type": "Representative",
        "state": "Connecticut",
        "birth_date": "August 19, 1770",
        "death_date": "February 3, 1842",
        "age_at_congress": 44,
        "age_at_death": 71,
        "sex": "male"
    },
    {
        "name": "Jonathan O. Moseley",
        "URL": "https://en.wikipedia.org/wiki/Jonathan_O._Moseley",
        "party": "Federalist",
        "type": "Representative",
        "state": "Connecticut",
        "birth_date": "April 9, 1762",
        "death_date": "September 9, 1838",
        "age_at_congress": 52,
        "age_at_death": 76,
        "sex": "male"
    },
    {
        "name": "Timothy Pitkin",
        "URL": "https://en.wikipedia.org/wiki/Timothy_Pitkin",
        "party": "Federalist",
        "type": "Representative",
        "state": "Connecticut",
        "birth_date": "January 21, 1766",
        "death_date": "December 18, 1847",
        "age_at_congress": 49,
        "age_at_death": 81,
        "sex": "male"
    },
    {
        "name": "Lewis B. Sturges",
        "URL": "https://en.wikipedia.org/wiki/Lewis_B._Sturges",
        "party": "Federalist",
        "type": "Representative",
        "state": "Connecticut",
        "birth_date": "March 15, 1763",
        "death_date": "March 30, 1844",
        "age_at_congress": 52,
        "age_at_death": 81,
        "sex": "male"
    },
    {
        "name": "Benjamin Tallmadge",
        "URL": "https://en.wikipedia.org/wiki/Benjamin_Tallmadge",
        "party": "Federalist",
        "type": "Representative",
        "state": "Connecticut",
        "birth_date": "February 25, 1754",
        "death_date": "March 7, 1835",
        "age_at_congress": 61,
        "age_at_death": 81,
        "sex": "male"
    },
    {
        "name": "Thomas Clayton",
        "URL": "https://en.wikipedia.org/wiki/Thomas_Clayton",
        "party": "Federalist",
        "type": "Representative",
        "state": "Delaware",
        "birth_date": "July 1, 1777",
        "death_date": "August 21, 1854",
        "age_at_congress": 37,
        "age_at_death": 77,
        "sex": "male"
    },
    {
        "name": "Thomas Cooper",
        "URL": "https://en.wikipedia.org/wiki/Thomas_Cooper_(American_politician,_born_1764)",
        "party": "Federalist",
        "type": "Representative",
        "state": "Delaware",
        "birth_date": "January 1, 1764",
        "death_date": "January 1, 1829",
        "age_at_congress": 51,
        "age_at_death": 65,
        "sex": "male"
    },
    {
        "name": "Alfred Cuthbert",
        "URL": "https://en.wikipedia.org/wiki/Alfred_Cuthbert",
        "party": "Democratic-Republican",
        "type": "Representative",
        "state": "Georgia",
        "birth_date": "December 23, 1785",
        "death_date": "July 9, 1856",
        "age_at_congress": 29,
        "age_at_death": 70,
        "sex": "male"
    },
    {
        "name": "John Forsyth",
        "URL": "https://en.wikipedia.org/wiki/John_Forsyth_(politician)",
        "party": "Democratic-Republican",
        "type": "Representative",
        "state": "Georgia",
        "birth_date": "October 22, 1780",
        "death_date": "October 21, 1841",
        "age_at_congress": 34,
        "age_at_death": 61,
        "sex": "male"
    },
    {
        "name": "Bolling Hall",
        "URL": "https://en.wikipedia.org/wiki/Bolling_Hall",
        "party": "Democratic-Republican",
        "type": "Representative",
        "state": "Georgia",
        "birth_date": "December 25, 1767",
        "death_date": "February 25, 1836",
        "age_at_congress": 47,
        "age_at_death": 68,
        "sex": "male"
    },
    {
        "name": "Wilson Lumpkin",
        "URL": "https://en.wikipedia.org/wiki/Wilson_Lumpkin",
        "party": "Democratic-Republican",
        "type": "Representative",
        "state": "Georgia",
        "birth_date": "January 14, 1783",
        "death_date": "December 28, 1870",
        "age_at_congress": 32,
        "age_at_death": 88,
        "sex": "male"
    },
    {
        "name": "Thomas Telfair",
        "URL": "https://en.wikipedia.org/wiki/Thomas_Telfair",
        "party": "Democratic-Republican",
        "type": "Representative",
        "state": "Georgia",
        "birth_date": "March 2, 1780",
        "death_date": "February 18, 1818",
        "age_at_congress": 35,
        "age_at_death": 37,
        "sex": "male"
    },
    {
        "name": "Richard Henry Wilde",
        "URL": "https://en.wikipedia.org/wiki/Richard_Henry_Wilde",
        "party": "Democratic-Republican",
        "type": "Representative",
        "state": "Georgia",
        "birth_date": "September 24, 1789",
        "death_date": "September 10, 1847",
        "age_at_congress": 25,
        "age_at_death": 57,
        "sex": "male"
    },
    {
        "name": "William Hendricks",
        "URL": "https://en.wikipedia.org/wiki/William_Hendricks",
        "party": "Democratic-Republican",
        "type": "Representative",
        "state": "Indiana",
        "birth_date": "November 12, 1782",
        "death_date": "May 16, 1850",
        "age_at_congress": 32,
        "age_at_death": 67,
        "sex": "male"
    },
    {
        "name": "James Clark",
        "URL": "https://en.wikipedia.org/wiki/James_Clark_(Kentucky_politician)",
        "party": "Democratic-Republican",
        "type": "Representative",
        "state": "Kentucky",
        "birth_date": "January 16, 1779",
        "death_date": "August 27, 1839",
        "age_at_congress": 36,
        "age_at_death": 60,
        "sex": "male"
    },
    {
        "name": "Henry Clay",
        "URL": "https://en.wikipedia.org/wiki/Henry_Clay",
        "party": "Democratic-Republican",
        "type": "Representative",
        "state": "Kentucky",
        "birth_date": "April 12, 1777",
        "death_date": "June 29, 1852",
        "age_at_congress": 37,
        "age_at_death": 75,
        "sex": "male"
    },
    {
        "name": "Richard M. Johnson",
        "URL": "https://en.wikipedia.org/wiki/Richard_Mentor_Johnson",
        "party": "Democratic-Republican",
        "type": "Representative",
        "state": "Kentucky",
        "birth_date": "October 17, 1780",
        "death_date": "November 19, 1850",
        "age_at_congress": 34,
        "age_at_death": 70,
        "sex": "male"
    },
    {
        "name": "Joseph Desha",
        "URL": "https://en.wikipedia.org/wiki/Joseph_Desha",
        "party": "Democratic-Republican",
        "type": "Representative",
        "state": "Kentucky",
        "birth_date": "December 9, 1768",
        "death_date": "October 11, 1842",
        "age_at_congress": 46,
        "age_at_death": 73,
        "sex": "male"
    },
    {
        "name": "Alney McLean",
        "URL": "https://en.wikipedia.org/wiki/Alney_McLean",
        "party": "Democratic-Republican",
        "type": "Representative",
        "state": "Kentucky",
        "birth_date": "June 10, 1779",
        "death_date": "December 30, 1841",
        "age_at_congress": 35,
        "age_at_death": 62,
        "sex": "male"
    },
    {
        "name": "Solomon P. Sharp",
        "URL": "https://en.wikipedia.org/wiki/Solomon_P._Sharp",
        "party": "Democratic-Republican",
        "type": "Representative",
        "state": "Kentucky",
        "birth_date": "August 22, 1787",
        "death_date": "November 7, 1825",
        "age_at_congress": 27,
        "age_at_death": 38,
        "sex": "male"
    },
    {
        "name": "Samuel McKee",
        "URL": "https://en.wikipedia.org/wiki/Samuel_McKee_(1774)",
        "party": "Democratic-Republican",
        "type": "Representative",
        "state": "Kentucky",
        "birth_date": "October 13, 1774",
        "death_date": "October 16, 1826",
        "age_at_congress": 40,
        "age_at_death": 52,
        "sex": "male"
    },
    {
        "name": "Stephen Ormsby",
        "URL": "https://en.wikipedia.org/wiki/Stephen_Ormsby",
        "party": "Democratic-Republican",
        "type": "Representative",
        "state": "Kentucky",
        "birth_date": "January 1, 1759",
        "death_date": "March 4, 1844",
        "age_at_congress": 56,
        "age_at_death": 85,
        "sex": "male"
    },
    {
        "name": "Micah Taul",
        "URL": "https://en.wikipedia.org/wiki/Micah_Taul",
        "party": "Democratic-Republican",
        "type": "Representative",
        "state": "Kentucky",
        "birth_date": "May 14, 1785",
        "death_date": "May 27, 1850",
        "age_at_congress": 29,
        "age_at_death": 65,
        "sex": "male"
    },
    {
        "name": "Benjamin Hardin",
        "URL": "https://en.wikipedia.org/wiki/Benjamin_Hardin",
        "party": "Democratic-Republican",
        "type": "Representative",
        "state": "Kentucky",
        "birth_date": "February 29, 1784",
        "death_date": "September 24, 1852",
        "age_at_congress": 31,
        "age_at_death": 68,
        "sex": "male"
    },
    {
        "name": "Thomas B. Robertson",
        "URL": "https://en.wikipedia.org/wiki/Thomas_B._Robertson",
        "party": "Democratic-Republican",
        "type": "Representative",
        "state": "Louisiana",
        "birth_date": "February 27, 1779",
        "death_date": "October 5, 1828",
        "age_at_congress": 36,
        "age_at_death": 49,
        "sex": "male"
    },
    {
        "name": "Philip Stuart",
        "URL": "https://en.wikipedia.org/wiki/Philip_Stuart",
        "party": "Federalist",
        "type": "Representative",
        "state": "Maryland",
        "birth_date": "January 1, 1760",
        "death_date": "August 14, 1830",
        "age_at_congress": 55,
        "age_at_death": 70,
        "sex": "male"
    },
    {
        "name": "John C. Herbert",
        "URL": "https://en.wikipedia.org/wiki/John_Carlyle_Herbert",
        "party": "Federalist",
        "type": "Representative",
        "state": "Maryland",
        "birth_date": "August 16, 1775",
        "death_date": "September 1, 1846",
        "age_at_congress": 39,
        "age_at_death": 71,
        "sex": "male"
    },
    {
        "name": "Alexander C. Hanson",
        "URL": "https://en.wikipedia.org/wiki/Alexander_Contee_Hanson",
        "party": "Federalist",
        "type": "Representative",
        "state": "Maryland",
        "birth_date": "February 27, 1786",
        "death_date": "April 23, 1819",
        "age_at_congress": 29,
        "age_at_death": 33,
        "sex": "male"
    },
    {
        "name": "George Baer Jr.",
        "URL": "https://en.wikipedia.org/wiki/George_Baer_Jr.",
        "party": "Federalist",
        "type": "Representative",
        "state": "Maryland",
        "birth_date": "January 1, 1763",
        "death_date": "April 3, 1834",
        "age_at_congress": 52,
        "age_at_death": 71,
        "sex": "male"
    },
    {
        "name": "Nicholas R. Moore",
        "URL": "https://en.wikipedia.org/wiki/Nicholas_R._Moore",
        "party": "Democratic-Republican",
        "type": "Representative",
        "state": "Maryland",
        "birth_date": "July 21, 1756",
        "death_date": "October 7, 1816",
        "age_at_congress": 58,
        "age_at_death": 60,
        "sex": "male"
    },
    {
        "name": "William Pinkney",
        "URL": "https://en.wikipedia.org/wiki/William_Pinkney",
        "party": "Democratic-Republican",
        "type": "Representative",
        "state": "Maryland",
        "birth_date": "March 17, 1764",
        "death_date": "February 25, 1822",
        "age_at_congress": 50,
        "age_at_death": 57,
        "sex": "male"
    },
    {
        "name": "Stevenson Archer",
        "URL": "https://en.wikipedia.org/wiki/Stevenson_Archer_(1786%E2%80%931848)",
        "party": "Democratic-Republican",
        "type": "Representative",
        "state": "Maryland",
        "birth_date": "October 11, 1786",
        "death_date": "June 26, 1848",
        "age_at_congress": 28,
        "age_at_death": 61,
        "sex": "male"
    },
    {
        "name": "Robert Wright",
        "URL": "https://en.wikipedia.org/wiki/Robert_Wright_(Maryland_politician)",
        "party": "Democratic-Republican",
        "type": "Representative",
        "state": "Maryland",
        "birth_date": "November 20, 1752",
        "death_date": "September 7, 1826",
        "age_at_congress": 62,
        "age_at_death": 73,
        "sex": "male"
    },
    {
        "name": "Charles Goldsborough",
        "URL": "https://en.wikipedia.org/wiki/Charles_Goldsborough",
        "party": "Federalist",
        "type": "Representative",
        "state": "Maryland",
        "birth_date": "July 15, 1765",
        "death_date": "December 13, 1834",
        "age_at_congress": 49,
        "age_at_death": 69,
        "sex": "male"
    },
    {
        "name": "Artemas Ward Jr.",
        "URL": "https://en.wikipedia.org/wiki/Artemas_Ward_Jr.",
        "party": "Federalist",
        "type": "Representative",
        "state": "Massachusetts",
        "birth_date": "January 9, 1762",
        "death_date": "October 7, 1847",
        "age_at_congress": 53,
        "age_at_death": 85,
        "sex": "male"
    },
    {
        "name": "Timothy Pickering",
        "URL": "https://en.wikipedia.org/wiki/Timothy_Pickering",
        "party": "Federalist",
        "type": "Representative",
        "state": "Massachusetts",
        "birth_date": "July 17, 1745",
        "death_date": "January 29, 1829",
        "age_at_congress": 69,
        "age_at_death": 83,
        "sex": "male"
    },
    {
        "name": "Jeremiah Nelson",
        "URL": "https://en.wikipedia.org/wiki/Jeremiah_Nelson",
        "party": "Federalist",
        "type": "Representative",
        "state": "Massachusetts",
        "birth_date": "September 14, 1769",
        "death_date": "October 2, 1838",
        "age_at_congress": 45,
        "age_at_death": 69,
        "sex": "male"
    },
    {
        "name": "Asahel Stearns",
        "URL": "https://en.wikipedia.org/wiki/Asahel_Stearns",
        "party": "Federalist",
        "type": "Representative",
        "state": "Massachusetts",
        "birth_date": "June 17, 1774",
        "death_date": "February 5, 1839",
        "age_at_congress": 40,
        "age_at_death": 64,
        "sex": "male"
    },
    {
        "name": "Elijah H. Mills",
        "URL": "https://en.wikipedia.org/wiki/Elijah_H._Mills",
        "party": "Federalist",
        "type": "Representative",
        "state": "Massachusetts",
        "birth_date": "December 1, 1776",
        "death_date": "May 5, 1829",
        "age_at_congress": 38,
        "age_at_death": 52,
        "sex": "male"
    },
    {
        "name": "Samuel Taggart",
        "URL": "https://en.wikipedia.org/wiki/Samuel_Taggart",
        "party": "Federalist",
        "type": "Representative",
        "state": "Massachusetts",
        "birth_date": "March 24, 1754",
        "death_date": "April 25, 1825",
        "age_at_congress": 60,
        "age_at_death": 71,
        "sex": "male"
    },
    {
        "name": "John W. Hulbert",
        "URL": "https://en.wikipedia.org/wiki/John_W._Hulbert",
        "party": "Federalist",
        "type": "Representative",
        "state": "Massachusetts",
        "birth_date": "June 1, 1770",
        "death_date": "October 19, 1831",
        "age_at_congress": 44,
        "age_at_death": 61,
        "sex": "male"
    },
    {
        "name": "William Baylies",
        "URL": "https://en.wikipedia.org/wiki/William_Baylies",
        "party": "Federalist",
        "type": "Representative",
        "state": "Massachusetts",
        "birth_date": "September 15, 1776",
        "death_date": "September 27, 1865",
        "age_at_congress": 38,
        "age_at_death": 89,
        "sex": "male"
    },
    {
        "name": "John Reed Jr.",
        "URL": "https://en.wikipedia.org/wiki/John_Reed_Jr.",
        "party": "Federalist",
        "type": "Representative",
        "state": "Massachusetts",
        "birth_date": "September 2, 1781",
        "death_date": "November 25, 1860",
        "age_at_congress": 33,
        "age_at_death": 79,
        "sex": "male"
    },
    {
        "name": "Laban Wheaton",
        "URL": "https://en.wikipedia.org/wiki/Laban_Wheaton",
        "party": "Federalist",
        "type": "Representative",
        "state": "Massachusetts",
        "birth_date": "March 13, 1754",
        "death_date": "March 23, 1846",
        "age_at_congress": 61,
        "age_at_death": 92,
        "sex": "male"
    },
    {
        "name": "Elijah Brigham",
        "URL": "https://en.wikipedia.org/wiki/Elijah_Brigham",
        "party": "Federalist",
        "type": "Representative",
        "state": "Massachusetts",
        "birth_date": "July 7, 1751",
        "death_date": "February 22, 1816",
        "age_at_congress": 63,
        "age_at_death": 64,
        "sex": "male"
    },
    {
        "name": "Solomon Strong",
        "URL": "https://en.wikipedia.org/wiki/Solomon_Strong",
        "party": "Federalist",
        "type": "Representative",
        "state": "Massachusetts",
        "birth_date": "March 2, 1780",
        "death_date": "September 16, 1850",
        "age_at_congress": 35,
        "age_at_death": 70,
        "sex": "male"
    },
    {
        "name": "Nathaniel Ruggles",
        "URL": "https://en.wikipedia.org/wiki/Nathaniel_Ruggles",
        "party": "Federalist",
        "type": "Representative",
        "state": "Massachusetts",
        "birth_date": "November 11, 1761",
        "death_date": "December 19, 1819",
        "age_at_congress": 53,
        "age_at_death": 58,
        "sex": "male"
    },
    {
        "name": "Cyrus King",
        "URL": "https://en.wikipedia.org/wiki/Cyrus_King",
        "party": "Federalist",
        "type": "Representative",
        "state": "Massachusetts",
        "birth_date": "September 6, 1772",
        "death_date": "April 25, 1817",
        "age_at_congress": 42,
        "age_at_death": 44,
        "sex": "male"
    },
    {
        "name": "George Bradbury",
        "URL": "https://en.wikipedia.org/wiki/George_Bradbury_(American_politician)",
        "party": "Federalist",
        "type": "Representative",
        "state": "Massachusetts",
        "birth_date": "October 10, 1770",
        "death_date": "November 7, 1823",
        "age_at_congress": 44,
        "age_at_death": 53,
        "sex": "male"
    },
    {
        "name": "Benjamin Brown",
        "URL": "https://en.wikipedia.org/wiki/Benjamin_Brown_(Congressman)",
        "party": "Federalist",
        "type": "Representative",
        "state": "Massachusetts",
        "birth_date": "September 23, 1756",
        "death_date": "September 17, 1831",
        "age_at_congress": 58,
        "age_at_death": 75,
        "sex": "male"
    },
    {
        "name": "James Carr",
        "URL": "https://en.wikipedia.org/wiki/James_Carr_(Massachusetts)",
        "party": "Federalist",
        "type": "Representative",
        "state": "Massachusetts",
        "birth_date": "September 9, 1777",
        "death_date": "August 24, 1818",
        "age_at_congress": 37,
        "age_at_death": 40,
        "sex": "male"
    },
    {
        "name": "Thomas Rice",
        "URL": "https://en.wikipedia.org/wiki/Thomas_Rice_(Massachusetts_politician)",
        "party": "Federalist",
        "type": "Representative",
        "state": "Massachusetts",
        "birth_date": "March 30, 1768",
        "death_date": "August 25, 1854",
        "age_at_congress": 46,
        "age_at_death": 86,
        "sex": "male"
    },
    {
        "name": "Samuel S. Conner",
        "URL": "https://en.wikipedia.org/wiki/Samuel_S._Conner",
        "party": "Democratic-Republican",
        "type": "Representative",
        "state": "Massachusetts",
        "birth_date": "January 1, 1783",
        "death_date": "December 17, 1820",
        "age_at_congress": 32,
        "age_at_death": 37,
        "sex": "male"
    },
    {
        "name": "Albion K. Parris",
        "URL": "https://en.wikipedia.org/wiki/Albion_K._Parris",
        "party": "Democratic-Republican",
        "type": "Representative",
        "state": "Massachusetts",
        "birth_date": "January 19, 1788",
        "death_date": "February 11, 1857",
        "age_at_congress": 27,
        "age_at_death": 69,
        "sex": "male"
    },
    {
        "name": "Charles H. Atherton",
        "URL": "https://en.wikipedia.org/wiki/Charles_Humphrey_Atherton",
        "party": "Federalist",
        "type": "Representative",
        "state": "New Hampshire",
        "birth_date": "August 14, 1773",
        "death_date": "January 8, 1853",
        "age_at_congress": 41,
        "age_at_death": 79,
        "sex": "male"
    },
    {
        "name": "Bradbury Cilley",
        "URL": "https://en.wikipedia.org/wiki/Bradbury_Cilley",
        "party": "Federalist",
        "type": "Representative",
        "state": "New Hampshire",
        "birth_date": "February 1, 1760",
        "death_date": "December 17, 1831",
        "age_at_congress": 55,
        "age_at_death": 71,
        "sex": "male"
    },
    {
        "name": "William Hale",
        "URL": "https://en.wikipedia.org/wiki/William_Hale_(New_Hampshire_politician)",
        "party": "Federalist",
        "type": "Representative",
        "state": "New Hampshire",
        "birth_date": "August 6, 1765",
        "death_date": "November 8, 1848",
        "age_at_congress": 49,
        "age_at_death": 83,
        "sex": "male"
    },
    {
        "name": "Roger Vose",
        "URL": "https://en.wikipedia.org/wiki/Roger_Vose",
        "party": "Federalist",
        "type": "Representative",
        "state": "New Hampshire",
        "birth_date": "February 24, 1763",
        "death_date": "October 26, 1841",
        "age_at_congress": 52,
        "age_at_death": 78,
        "sex": "male"
    },
    {
        "name": "Daniel Webster",
        "URL": "https://en.wikipedia.org/wiki/Daniel_Webster",
        "party": "Federalist",
        "type": "Representative",
        "state": "New Hampshire",
        "birth_date": "January 18, 1782",
        "death_date": "October 24, 1852",
        "age_at_congress": 33,
        "age_at_death": 70,
        "sex": "male"
    },
    {
        "name": "Jeduthun Wilcox",
        "URL": "https://en.wikipedia.org/wiki/Jeduthun_Wilcox",
        "party": "Federalist",
        "type": "Representative",
        "state": "New Hampshire",
        "birth_date": "November 18, 1768",
        "death_date": "July 18, 1838",
        "age_at_congress": 46,
        "age_at_death": 69,
        "sex": "male"
    },
    {
        "name": "Ezra Baker",
        "URL": "https://en.wikipedia.org/wiki/Ezra_Baker",
        "party": "Democratic-Republican",
        "type": "Representative",
        "state": "New Jersey",
        "birth_date": "January 1, 1765",
        "death_date": null,
        "age_at_congress": 50,
        "age_at_death": null,
        "sex": "male"
    },
    {
        "name": "Ephraim Bateman",
        "URL": "https://en.wikipedia.org/wiki/Ephraim_Bateman",
        "party": "Democratic-Republican",
        "type": "Representative",
        "state": "New Jersey",
        "birth_date": "July 9, 1780",
        "death_date": "January 28, 1829",
        "age_at_congress": 34,
        "age_at_death": 48,
        "sex": "male"
    },
    {
        "name": "Benjamin Bennet",
        "URL": "https://en.wikipedia.org/wiki/Benjamin_Bennet_(politician)",
        "party": "Democratic-Republican",
        "type": "Representative",
        "state": "New Jersey",
        "birth_date": "October 31, 1764",
        "death_date": "October 8, 1840",
        "age_at_congress": 50,
        "age_at_death": 75,
        "sex": "male"
    },
    {
        "name": "Lewis Condict",
        "URL": "https://en.wikipedia.org/wiki/Lewis_Condict",
        "party": "Democratic-Republican",
        "type": "Representative",
        "state": "New Jersey",
        "birth_date": "March 3, 1772",
        "death_date": "May 26, 1862",
        "age_at_congress": 43,
        "age_at_death": 90,
        "sex": "male"
    },
    {
        "name": "Henry Southard",
        "URL": "https://en.wikipedia.org/wiki/Henry_Southard",
        "party": "Democratic-Republican",
        "type": "Representative",
        "state": "New Jersey",
        "birth_date": "October 7, 1747",
        "death_date": "May 22, 1842",
        "age_at_congress": 67,
        "age_at_death": 94,
        "sex": "male"
    },
    {
        "name": "Thomas Ward",
        "URL": "https://en.wikipedia.org/wiki/Thomas_Ward_(New_Jersey_politician)",
        "party": "Democratic-Republican",
        "type": "Representative",
        "state": "New Jersey",
        "birth_date": "January 1, 1759",
        "death_date": "March 4, 1842",
        "age_at_congress": 56,
        "age_at_death": 83,
        "sex": "male"
    },
    {
        "name": "Henry Crocheron",
        "URL": "https://en.wikipedia.org/wiki/Henry_Crocheron",
        "party": "Democratic-Republican",
        "type": "Representative",
        "state": "New York",
        "birth_date": "December 26, 1772",
        "death_date": "November 8, 1819",
        "age_at_congress": 42,
        "age_at_death": 46,
        "sex": "male"
    },
    {
        "name": "George Townsend",
        "URL": "https://en.wikipedia.org/wiki/George_Townsend_(politician)",
        "party": "Democratic-Republican",
        "type": "Representative",
        "state": "New York",
        "birth_date": "December 21, 1768",
        "death_date": "August 17, 1844",
        "age_at_congress": 46,
        "age_at_death": 75,
        "sex": "male"
    },
    {
        "name": "William Irving",
        "URL": "https://en.wikipedia.org/wiki/William_Irving_(New_York)",
        "party": "Democratic-Republican",
        "type": "Representative",
        "state": "New York",
        "birth_date": "August 15, 1766",
        "death_date": "November 9, 1821",
        "age_at_congress": 48,
        "age_at_death": 55,
        "sex": "male"
    },
    {
        "name": "Peter H. Wendover",
        "URL": "https://en.wikipedia.org/wiki/Peter_H._Wendover",
        "party": "Democratic-Republican",
        "type": "Representative",
        "state": "New York",
        "birth_date": "August 1, 1768",
        "death_date": "September 24, 1834",
        "age_at_congress": 46,
        "age_at_death": 66,
        "sex": "male"
    },
    {
        "name": "Jonathan Ward",
        "URL": "https://en.wikipedia.org/wiki/Jonathan_Ward_(New_York)",
        "party": "Democratic-Republican",
        "type": "Representative",
        "state": "New York",
        "birth_date": "September 21, 1768",
        "death_date": "September 28, 1842",
        "age_at_congress": 46,
        "age_at_death": 74,
        "sex": "male"
    },
    {
        "name": "Abraham H. Schenck",
        "URL": "https://en.wikipedia.org/wiki/Abraham_H._Schenck",
        "party": "Democratic-Republican",
        "type": "Representative",
        "state": "New York",
        "birth_date": "January 22, 1775",
        "death_date": "June 1, 1831",
        "age_at_congress": 40,
        "age_at_death": 56,
        "sex": "male"
    },
    {
        "name": "Thomas P. Grosvenor",
        "URL": "https://en.wikipedia.org/wiki/Thomas_P._Grosvenor",
        "party": "Federalist",
        "type": "Representative",
        "state": "New York",
        "birth_date": "December 20, 1778",
        "death_date": "April 24, 1817",
        "age_at_congress": 36,
        "age_at_death": 38,
        "sex": "male"
    },
    {
        "name": "Jonathan Fisk",
        "URL": "https://en.wikipedia.org/wiki/Jonathan_Fisk",
        "party": "Democratic-Republican",
        "type": "Representative",
        "state": "New York",
        "birth_date": "September 26, 1778",
        "death_date": "July 13, 1832",
        "age_at_congress": 36,
        "age_at_death": 53,
        "sex": "male"
    },
    {
        "name": "Samuel Betts",
        "URL": "https://en.wikipedia.org/wiki/Samuel_Betts",
        "party": "Democratic-Republican",
        "type": "Representative",
        "state": "New York",
        "birth_date": "June 8, 1786",
        "death_date": "November 3, 1868",
        "age_at_congress": 28,
        "age_at_death": 82,
        "sex": "male"
    },
    {
        "name": "Erastus Root",
        "URL": "https://en.wikipedia.org/wiki/Erastus_Root",
        "party": "Democratic-Republican",
        "type": "Representative",
        "state": "New York",
        "birth_date": "March 16, 1773",
        "death_date": "December 24, 1846",
        "age_at_congress": 41,
        "age_at_death": 73,
        "sex": "male"
    },
    {
        "name": "John Lovett",
        "URL": "https://en.wikipedia.org/wiki/John_Lovett_(American_politician)",
        "party": "Federalist",
        "type": "Representative",
        "state": "New York",
        "birth_date": "February 20, 1761",
        "death_date": "August 12, 1818",
        "age_at_congress": 54,
        "age_at_death": 57,
        "sex": "male"
    },
    {
        "name": "Hosea Moffitt",
        "URL": "https://en.wikipedia.org/wiki/Hosea_Moffitt",
        "party": "Federalist",
        "type": "Representative",
        "state": "New York",
        "birth_date": "November 17, 1757",
        "death_date": "August 31, 1825",
        "age_at_congress": 57,
        "age_at_death": 67,
        "sex": "male"
    },
    {
        "name": "John W. Taylor",
        "URL": "https://en.wikipedia.org/wiki/John_W._Taylor_(politician)",
        "party": "Democratic-Republican",
        "type": "Representative",
        "state": "New York",
        "birth_date": "March 26, 1784",
        "death_date": "September 18, 1854",
        "age_at_congress": 30,
        "age_at_death": 70,
        "sex": "male"
    },
    {
        "name": "Asa Adgate",
        "URL": "https://en.wikipedia.org/wiki/Asa_Adgate",
        "party": "Democratic-Republican",
        "type": "Representative",
        "state": "New York",
        "birth_date": "November 17, 1767",
        "death_date": "February 15, 1832",
        "age_at_congress": 47,
        "age_at_death": 64,
        "sex": "male"
    },
    {
        "name": "John Savage",
        "URL": "https://en.wikipedia.org/wiki/John_Savage_(representative)",
        "party": "Democratic-Republican",
        "type": "Representative",
        "state": "New York",
        "birth_date": "February 22, 1779",
        "death_date": "October 19, 1863",
        "age_at_congress": 36,
        "age_at_death": 84,
        "sex": "male"
    },
    {
        "name": "John B. Yates",
        "URL": "https://en.wikipedia.org/wiki/John_B._Yates",
        "party": "Democratic-Republican",
        "type": "Representative",
        "state": "New York",
        "birth_date": "February 1, 1784",
        "death_date": "July 10, 1836",
        "age_at_congress": 31,
        "age_at_death": 52,
        "sex": "male"
    },
    {
        "name": "Daniel Cady",
        "URL": "https://en.wikipedia.org/wiki/Daniel_Cady",
        "party": "Federalist",
        "type": "Representative",
        "state": "New York",
        "birth_date": "April 29, 1773",
        "death_date": "October 31, 1859",
        "age_at_congress": 41,
        "age_at_death": 86,
        "sex": "male"
    },
    {
        "name": "James Birdsall",
        "URL": "https://en.wikipedia.org/wiki/James_Birdsall",
        "party": "Democratic-Republican",
        "type": "Representative",
        "state": "New York",
        "birth_date": "January 1, 1783",
        "death_date": "July 20, 1856",
        "age_at_congress": 32,
        "age_at_death": 73,
        "sex": "male"
    },
    {
        "name": "Jabez D. Hammond",
        "URL": "https://en.wikipedia.org/wiki/Jabez_Delano_Hammond",
        "party": "Democratic-Republican",
        "type": "Representative",
        "state": "New York",
        "birth_date": "August 2, 1778",
        "death_date": "August 18, 1855",
        "age_at_congress": 36,
        "age_at_death": 77,
        "sex": "male"
    },
    {
        "name": "Thomas R. Gold",
        "URL": "https://en.wikipedia.org/wiki/Thomas_R._Gold",
        "party": "Federalist",
        "type": "Representative",
        "state": "New York",
        "birth_date": "November 4, 1764",
        "death_date": "October 24, 1827",
        "age_at_congress": 50,
        "age_at_death": 63,
        "sex": "male"
    },
    {
        "name": "Westel Willoughby Jr.",
        "URL": "https://en.wikipedia.org/wiki/Westel_Willoughby_Jr.",
        "party": "Democratic-Republican",
        "type": "Representative",
        "state": "New York",
        "birth_date": "November 20, 1769",
        "death_date": "October 3, 1844",
        "age_at_congress": 45,
        "age_at_death": 74,
        "sex": "male"
    },
    {
        "name": "Moss Kent",
        "URL": "https://en.wikipedia.org/wiki/Moss_Kent",
        "party": "Federalist",
        "type": "Representative",
        "state": "New York",
        "birth_date": "April 3, 1766",
        "death_date": "May 30, 1838",
        "age_at_congress": 48,
        "age_at_death": 72,
        "sex": "male"
    },
    {
        "name": "Victory Birdseye",
        "URL": "https://en.wikipedia.org/wiki/Victory_Birdseye",
        "party": "Democratic-Republican",
        "type": "Representative",
        "state": "New York",
        "birth_date": "December 25, 1782",
        "death_date": "September 16, 1853",
        "age_at_congress": 32,
        "age_at_death": 70,
        "sex": "male"
    },
    {
        "name": "Oliver C. Comstock",
        "URL": "https://en.wikipedia.org/wiki/Oliver_C._Comstock",
        "party": "Democratic-Republican",
        "type": "Representative",
        "state": "New York",
        "birth_date": "March 1, 1780",
        "death_date": "January 11, 1860",
        "age_at_congress": 35,
        "age_at_death": 79,
        "sex": "male"
    },
    {
        "name": "Enos T. Throop",
        "URL": "https://en.wikipedia.org/wiki/Enos_T._Throop",
        "party": "Democratic-Republican",
        "type": "Representative",
        "state": "New York",
        "birth_date": "August 21, 1784",
        "death_date": "November 1, 1874",
        "age_at_congress": 30,
        "age_at_death": 90,
        "sex": "male"
    },
    {
        "name": "Micah Brooks",
        "URL": "https://en.wikipedia.org/wiki/Micah_Brooks",
        "party": "Democratic-Republican",
        "type": "Representative",
        "state": "New York",
        "birth_date": "May 14, 1775",
        "death_date": "July 7, 1857",
        "age_at_congress": 39,
        "age_at_death": 82,
        "sex": "male"
    },
    {
        "name": "Peter B. Porter",
        "URL": "https://en.wikipedia.org/wiki/Peter_Buell_Porter",
        "party": "Democratic-Republican",
        "type": "Representative",
        "state": "New York",
        "birth_date": "August 14, 1773",
        "death_date": "March 20, 1844",
        "age_at_congress": 41,
        "age_at_death": 70,
        "sex": "male"
    },
    {
        "name": "William H. Murfree",
        "URL": "https://en.wikipedia.org/wiki/William_H._Murfree",
        "party": "Democratic-Republican",
        "type": "Representative",
        "state": "North Carolina",
        "birth_date": "October 2, 1781",
        "death_date": "January 19, 1827",
        "age_at_congress": 33,
        "age_at_death": 45,
        "sex": "male"
    },
    {
        "name": "Joseph H. Bryan",
        "URL": "https://en.wikipedia.org/wiki/Joseph_Hunter_Bryan",
        "party": "Democratic-Republican",
        "type": "Representative",
        "state": "North Carolina",
        "birth_date": "April 9, 1782",
        "death_date": "December 28, 1839",
        "age_at_congress": 32,
        "age_at_death": 57,
        "sex": "male"
    },
    {
        "name": "James W. Clark",
        "URL": "https://en.wikipedia.org/wiki/James_West_Clark",
        "party": "Democratic-Republican",
        "type": "Representative",
        "state": "North Carolina",
        "birth_date": "October 15, 1779",
        "death_date": "December 20, 1843",
        "age_at_congress": 35,
        "age_at_death": 64,
        "sex": "male"
    },
    {
        "name": "William Gaston",
        "URL": "https://en.wikipedia.org/wiki/William_Gaston",
        "party": "Federalist",
        "type": "Representative",
        "state": "North Carolina",
        "birth_date": "September 19, 1778",
        "death_date": "January 23, 1844",
        "age_at_congress": 36,
        "age_at_death": 65,
        "sex": "male"
    },
    {
        "name": "William R. King",
        "URL": "https://en.wikipedia.org/wiki/William_R._King",
        "party": "Democratic-Republican",
        "type": "Representative",
        "state": "North Carolina",
        "birth_date": "April 7, 1786",
        "death_date": "April 18, 1853",
        "age_at_congress": 28,
        "age_at_death": 67,
        "sex": "male"
    },
    {
        "name": "Nathaniel Macon",
        "URL": "https://en.wikipedia.org/wiki/Nathaniel_Macon",
        "party": "Democratic-Republican",
        "type": "Representative",
        "state": "North Carolina",
        "birth_date": "December 17, 1757",
        "death_date": "June 29, 1837",
        "age_at_congress": 57,
        "age_at_death": 79,
        "sex": "male"
    },
    {
        "name": "John Culpepper",
        "URL": "https://en.wikipedia.org/wiki/John_Culpepper",
        "party": "Federalist",
        "type": "Representative",
        "state": "North Carolina",
        "birth_date": "January 1, 1761",
        "death_date": "January 1, 1841",
        "age_at_congress": 54,
        "age_at_death": 80,
        "sex": "male"
    },
    {
        "name": "Richard Stanford",
        "URL": "https://en.wikipedia.org/wiki/Richard_Stanford_(American_politician)",
        "party": "Democratic-Republican",
        "type": "Representative",
        "state": "North Carolina",
        "birth_date": "March 2, 1767",
        "death_date": "April 9, 1816",
        "age_at_congress": 48,
        "age_at_death": 49,
        "sex": "male"
    },
    {
        "name": "Bartlett Yancey",
        "URL": "https://en.wikipedia.org/wiki/Bartlett_Yancey",
        "party": "Democratic-Republican",
        "type": "Representative",
        "state": "North Carolina",
        "birth_date": "February 19, 1785",
        "death_date": "August 30, 1828",
        "age_at_congress": 30,
        "age_at_death": 43,
        "sex": "male"
    },
    {
        "name": "William C. Love",
        "URL": "https://en.wikipedia.org/wiki/William_Carter_Love",
        "party": "Democratic-Republican",
        "type": "Representative",
        "state": "North Carolina",
        "birth_date": "January 1, 1784",
        "death_date": "December 3, 1824",
        "age_at_congress": 31,
        "age_at_death": 40,
        "sex": "male"
    },
    {
        "name": "Daniel M. Forney",
        "URL": "https://en.wikipedia.org/wiki/Daniel_Munroe_Forney",
        "party": "Democratic-Republican",
        "type": "Representative",
        "state": "North Carolina",
        "birth_date": "May 1, 1784",
        "death_date": "October 15, 1847",
        "age_at_congress": 30,
        "age_at_death": 63,
        "sex": "male"
    },
    {
        "name": "Israel Pickens",
        "URL": "https://en.wikipedia.org/wiki/Israel_Pickens",
        "party": "Democratic-Republican",
        "type": "Representative",
        "state": "North Carolina",
        "birth_date": "January 30, 1780",
        "death_date": "April 24, 1827",
        "age_at_congress": 35,
        "age_at_death": 47,
        "sex": "male"
    },
    {
        "name": "Lewis Williams",
        "URL": "https://en.wikipedia.org/wiki/Lewis_Williams_(politician)",
        "party": "Democratic-Republican",
        "type": "Representative",
        "state": "North Carolina",
        "birth_date": "February 1, 1782",
        "death_date": "February 23, 1842",
        "age_at_congress": 33,
        "age_at_death": 60,
        "sex": "male"
    },
    {
        "name": "John McLean",
        "URL": "https://en.wikipedia.org/wiki/John_McLean",
        "party": "Democratic-Republican",
        "type": "Representative",
        "state": "Ohio",
        "birth_date": "March 11, 1785",
        "death_date": "April 4, 1861",
        "age_at_congress": 29,
        "age_at_death": 76,
        "sex": "male"
    },
    {
        "name": "John Alexander",
        "URL": "https://en.wikipedia.org/wiki/John_Alexander_(congressman)",
        "party": "Democratic-Republican",
        "type": "Representative",
        "state": "Ohio",
        "birth_date": "April 16, 1777",
        "death_date": "June 28, 1848",
        "age_at_congress": 37,
        "age_at_death": 71,
        "sex": "male"
    },
    {
        "name": "William Creighton Jr.",
        "URL": "https://en.wikipedia.org/wiki/William_Creighton_Jr.",
        "party": "Democratic-Republican",
        "type": "Representative",
        "state": "Ohio",
        "birth_date": "October 29, 1778",
        "death_date": "October 1, 1851",
        "age_at_congress": 36,
        "age_at_death": 72,
        "sex": "male"
    },
    {
        "name": "James Caldwell",
        "URL": "https://en.wikipedia.org/wiki/James_Caldwell_(representative)",
        "party": "Democratic-Republican",
        "type": "Representative",
        "state": "Ohio",
        "birth_date": "November 30, 1770",
        "death_date": "May 5, 1838",
        "age_at_congress": 44,
        "age_at_death": 67,
        "sex": "male"
    },
    {
        "name": "James Kilbourne",
        "URL": "https://en.wikipedia.org/wiki/James_Kilbourne",
        "party": "Democratic-Republican",
        "type": "Representative",
        "state": "Ohio",
        "birth_date": "October 19, 1770",
        "death_date": "April 9, 1850",
        "age_at_congress": 44,
        "age_at_death": 79,
        "sex": "male"
    },
    {
        "name": "David Clendenin",
        "URL": "https://en.wikipedia.org/wiki/David_Clendenin",
        "party": "Democratic-Republican",
        "type": "Representative",
        "state": "Ohio",
        "birth_date": null,
        "death_date": null,
        "age_at_congress": null,
        "age_at_death": null,
        "sex": "male"
    },
    {
        "name": "Joseph Hopkinson",
        "URL": "https://en.wikipedia.org/wiki/Joseph_Hopkinson",
        "party": "Federalist",
        "type": "Representative",
        "state": "Pennsylvania",
        "birth_date": "November 12, 1770",
        "death_date": "January 15, 1842",
        "age_at_congress": 44,
        "age_at_death": 71,
        "sex": "male"
    },
    {
        "name": "William Milnor",
        "URL": "https://en.wikipedia.org/wiki/William_Milnor",
        "party": "Federalist",
        "type": "Representative",
        "state": "Pennsylvania",
        "birth_date": "June 26, 1769",
        "death_date": "December 13, 1848",
        "age_at_congress": 45,
        "age_at_death": 79,
        "sex": "male"
    },
    {
        "name": "Thomas Smith",
        "URL": "https://en.wikipedia.org/wiki/Thomas_Smith_(Pennsylvania_congressman)",
        "party": "Federalist",
        "type": "Representative",
        "state": "Pennsylvania",
        "birth_date": "January 1, 1773",
        "death_date": "January 29, 1846",
        "age_at_congress": 42,
        "age_at_death": 73,
        "sex": "male"
    },
    {
        "name": "Jonathan Williams",
        "URL": "https://en.wikipedia.org/wiki/Jonathan_Williams_(engineer)",
        "party": "Democratic-Republican",
        "type": "Representative",
        "state": "Pennsylvania",
        "birth_date": "May 20, 1750",
        "death_date": "May 16, 1815",
        "age_at_congress": 64,
        "age_at_death": 65,
        "sex": "male"
    },
    {
        "name": "William Darlington",
        "URL": "https://en.wikipedia.org/wiki/William_Darlington",
        "party": "Democratic-Republican",
        "type": "Representative",
        "state": "Pennsylvania",
        "birth_date": "April 28, 1782",
        "death_date": "April 23, 1863",
        "age_at_congress": 32,
        "age_at_death": 81,
        "sex": "male"
    },
    {
        "name": "John Hahn",
        "URL": "https://en.wikipedia.org/wiki/John_Hahn_(politician)",
        "party": "Democratic-Republican",
        "type": "Representative",
        "state": "Pennsylvania",
        "birth_date": "October 30, 1776",
        "death_date": "February 26, 1823",
        "age_at_congress": 38,
        "age_at_death": 46,
        "sex": "male"
    },
    {
        "name": "James M. Wallace",
        "URL": "https://en.wikipedia.org/wiki/James_M._Wallace",
        "party": "Democratic-Republican",
        "type": "Representative",
        "state": "Pennsylvania",
        "birth_date": "January 1, 1750",
        "death_date": "December 17, 1823",
        "age_at_congress": 65,
        "age_at_death": 74,
        "sex": "male"
    },
    {
        "name": "John Whiteside",
        "URL": "https://en.wikipedia.org/wiki/John_Whiteside",
        "party": "Democratic-Republican",
        "type": "Representative",
        "state": "Pennsylvania",
        "birth_date": "January 1, 1773",
        "death_date": "July 28, 1830",
        "age_at_congress": 42,
        "age_at_death": 57,
        "sex": "male"
    },
    {
        "name": "Hugh Glasgow",
        "URL": "https://en.wikipedia.org/wiki/Hugh_Glasgow",
        "party": "Democratic-Republican",
        "type": "Representative",
        "state": "Pennsylvania",
        "birth_date": "September 8, 1769",
        "death_date": "January 31, 1818",
        "age_at_congress": 45,
        "age_at_death": 48,
        "sex": "male"
    },
    {
        "name": "William Crawford",
        "URL": "https://en.wikipedia.org/wiki/William_Crawford_(Pennsylvania)",
        "party": "Democratic-Republican",
        "type": "Representative",
        "state": "Pennsylvania",
        "birth_date": "January 1, 1760",
        "death_date": "October 23, 1823",
        "age_at_congress": 55,
        "age_at_death": 63,
        "sex": "male"
    },
    {
        "name": "William Maclay",
        "URL": "https://en.wikipedia.org/wiki/William_Maclay_(Representative)",
        "party": "Democratic-Republican",
        "type": "Representative",
        "state": "Pennsylvania",
        "birth_date": "March 22, 1765",
        "death_date": "January 4, 1825",
        "age_at_congress": 49,
        "age_at_death": 59,
        "sex": "male"
    },
    {
        "name": "Samuel D. Ingham",
        "URL": "https://en.wikipedia.org/wiki/Samuel_D._Ingham",
        "party": "Democratic-Republican",
        "type": "Representative",
        "state": "Pennsylvania",
        "birth_date": "September 16, 1779",
        "death_date": "June 5, 1860",
        "age_at_congress": 35,
        "age_at_death": 80,
        "sex": "male"
    },
    {
        "name": "John Ross",
        "URL": "https://en.wikipedia.org/wiki/John_Ross_(representative)",
        "party": "Democratic-Republican",
        "type": "Representative",
        "state": "Pennsylvania",
        "birth_date": "February 24, 1770",
        "death_date": "January 31, 1834",
        "age_at_congress": 45,
        "age_at_death": 63,
        "sex": "male"
    },
    {
        "name": "Joseph Hiester",
        "URL": "https://en.wikipedia.org/wiki/Joseph_Hiester",
        "party": "Democratic-Republican",
        "type": "Representative",
        "state": "Pennsylvania",
        "birth_date": "November 18, 1752",
        "death_date": "June 10, 1832",
        "age_at_congress": 62,
        "age_at_death": 79,
        "sex": "male"
    },
    {
        "name": "William Piper",
        "URL": "https://en.wikipedia.org/wiki/William_Piper",
        "party": "Democratic-Republican",
        "type": "Representative",
        "state": "Pennsylvania",
        "birth_date": "January 1, 1774",
        "death_date": "January 1, 1852",
        "age_at_congress": 41,
        "age_at_death": 78,
        "sex": "male"
    },
    {
        "name": "David Bard",
        "URL": "https://en.wikipedia.org/wiki/David_Bard",
        "party": "Democratic-Republican",
        "type": "Representative",
        "state": "Pennsylvania",
        "birth_date": "January 1, 1744",
        "death_date": "March 12, 1815",
        "age_at_congress": 71,
        "age_at_death": 71,
        "sex": "male"
    },
    {
        "name": "Jared Irwin",
        "URL": "https://en.wikipedia.org/wiki/Jared_Irwin_(Pennsylvania_politician)",
        "party": "Democratic-Republican",
        "type": "Representative",
        "state": "Pennsylvania",
        "birth_date": "January 19, 1768",
        "death_date": "September 20, 1818",
        "age_at_congress": 47,
        "age_at_death": 50,
        "sex": "male"
    },
    {
        "name": "William Wilson",
        "URL": "https://en.wikipedia.org/wiki/William_Wilson_(Pennsylvania_politician)",
        "party": "Democratic-Republican",
        "type": "Representative",
        "state": "Pennsylvania",
        "birth_date": null,
        "death_date": null,
        "age_at_congress": null,
        "age_at_death": null,
        "sex": "male"
    },
    {
        "name": "William Findley",
        "URL": "https://en.wikipedia.org/wiki/William_Findley",
        "party": "Democratic-Republican",
        "type": "Representative",
        "state": "Pennsylvania",
        "birth_date": "January 1, 1741",
        "death_date": "April 4, 1821",
        "age_at_congress": 74,
        "age_at_death": 80,
        "sex": "male"
    },
    {
        "name": "Aaron Lyle",
        "URL": "https://en.wikipedia.org/wiki/Aaron_Lyle",
        "party": "Democratic-Republican",
        "type": "Representative",
        "state": "Pennsylvania",
        "birth_date": "November 17, 1759",
        "death_date": "September 24, 1825",
        "age_at_congress": 55,
        "age_at_death": 65,
        "sex": "male"
    },
    {
        "name": "Isaac Griffin",
        "URL": "https://en.wikipedia.org/wiki/Isaac_Griffin",
        "party": "Democratic-Republican",
        "type": "Representative",
        "state": "Pennsylvania",
        "birth_date": "February 27, 1756",
        "death_date": "October 12, 1827",
        "age_at_congress": 59,
        "age_at_death": 71,
        "sex": "male"
    },
    {
        "name": "John Woods",
        "URL": "https://en.wikipedia.org/wiki/John_Woods_(Pennsylvania_politician)",
        "party": "Federalist",
        "type": "Representative",
        "state": "Pennsylvania",
        "birth_date": "January 1, 1761",
        "death_date": "December 16, 1816",
        "age_at_congress": 54,
        "age_at_death": 55,
        "sex": "male"
    },
    {
        "name": "Thomas Wilson",
        "URL": "https://en.wikipedia.org/wiki/Thomas_Wilson_(Pennsylvania)",
        "party": "Democratic-Republican",
        "type": "Representative",
        "state": "Pennsylvania",
        "birth_date": "January 1, 1772",
        "death_date": "October 4, 1824",
        "age_at_congress": 43,
        "age_at_death": 52,
        "sex": "male"
    },
    {
        "name": "John L. Boss Jr.",
        "URL": "https://en.wikipedia.org/wiki/John_L._Boss_Jr.",
        "party": "Federalist",
        "type": "Representative",
        "state": "Rhode Island",
        "birth_date": "September 7, 1780",
        "death_date": "August 1, 1819",
        "age_at_congress": 34,
        "age_at_death": 38,
        "sex": "male"
    },
    {
        "name": "James B. Mason",
        "URL": "https://en.wikipedia.org/wiki/James_B._Mason",
        "party": "Federalist",
        "type": "Representative",
        "state": "Rhode Island",
        "birth_date": "January 28, 1775",
        "death_date": "August 31, 1819",
        "age_at_congress": 40,
        "age_at_death": 44,
        "sex": "male"
    },
    {
        "name": "Henry Middleton",
        "URL": "https://en.wikipedia.org/wiki/Henry_Middleton_(governor)",
        "party": "Democratic-Republican",
        "type": "Representative",
        "state": "South Carolina",
        "birth_date": "September 28, 1770",
        "death_date": "June 14, 1846",
        "age_at_congress": 44,
        "age_at_death": 75,
        "sex": "male"
    },
    {
        "name": "William Lowndes",
        "URL": "https://en.wikipedia.org/wiki/William_Lowndes_(congressman)",
        "party": "Democratic-Republican",
        "type": "Representative",
        "state": "South Carolina",
        "birth_date": "February 11, 1782",
        "death_date": "October 27, 1822",
        "age_at_congress": 33,
        "age_at_death": 40,
        "sex": "male"
    },
    {
        "name": "Benjamin Huger",
        "URL": "https://en.wikipedia.org/wiki/Benjamin_Huger_(1768%E2%80%931823)",
        "party": "Federalist",
        "type": "Representative",
        "state": "South Carolina",
        "birth_date": "January 1, 1768",
        "death_date": "July 7, 1823",
        "age_at_congress": 47,
        "age_at_death": 55,
        "sex": "male"
    },
    {
        "name": "John J. Chappell",
        "URL": "https://en.wikipedia.org/wiki/John_J._Chappell",
        "party": "Democratic-Republican",
        "type": "Representative",
        "state": "South Carolina",
        "birth_date": "January 19, 1782",
        "death_date": "May 23, 1871",
        "age_at_congress": 33,
        "age_at_death": 89,
        "sex": "male"
    },
    {
        "name": "William Woodward",
        "URL": "https://en.wikipedia.org/wiki/William_Woodward_(congressman)",
        "party": "Democratic-Republican",
        "type": "Representative",
        "state": "South Carolina",
        "birth_date": "October 7, 1762",
        "death_date": "July 23, 1820",
        "age_at_congress": 52,
        "age_at_death": 57,
        "sex": "male"
    },
    {
        "name": "John C. Calhoun",
        "URL": "https://en.wikipedia.org/wiki/John_C._Calhoun",
        "party": "Democratic-Republican",
        "type": "Representative",
        "state": "South Carolina",
        "birth_date": "March 18, 1782",
        "death_date": "March 31, 1850",
        "age_at_congress": 32,
        "age_at_death": 68,
        "sex": "male"
    },
    {
        "name": "John Taylor",
        "URL": "https://en.wikipedia.org/wiki/John_Taylor_(14th_Congress)",
        "party": "Democratic-Republican",
        "type": "Representative",
        "state": "South Carolina",
        "birth_date": null,
        "death_date": null,
        "age_at_congress": null,
        "age_at_death": null,
        "sex": "male"
    },
    {
        "name": "Thomas Moore",
        "URL": "https://en.wikipedia.org/wiki/Thomas_Moore_(congressman)",
        "party": "Democratic-Republican",
        "type": "Representative",
        "state": "South Carolina",
        "birth_date": "January 1, 1759",
        "death_date": "July 11, 1822",
        "age_at_congress": 56,
        "age_at_death": 63,
        "sex": "male"
    },
    {
        "name": "William Mayrant",
        "URL": "https://en.wikipedia.org/wiki/William_Mayrant",
        "party": "Democratic-Republican",
        "type": "Representative",
        "state": "South Carolina",
        "birth_date": "March 8, 1765",
        "death_date": "January 23, 1832",
        "age_at_congress": 50,
        "age_at_death": 66,
        "sex": "male"
    },
    {
        "name": "Samuel Powell",
        "URL": "https://en.wikipedia.org/wiki/Samuel_Powell",
        "party": "Democratic-Republican",
        "type": "Representative",
        "state": "Tennessee",
        "birth_date": "July 10, 1776",
        "death_date": "August 2, 1841",
        "age_at_congress": 38,
        "age_at_death": 65,
        "sex": "male"
    },
    {
        "name": "John Sevier",
        "URL": "https://en.wikipedia.org/wiki/John_Sevier",
        "party": "Democratic-Republican",
        "type": "Representative",
        "state": "Tennessee",
        "birth_date": "September 23, 1745",
        "death_date": "September 24, 1815",
        "age_at_congress": 69,
        "age_at_death": 70,
        "sex": "male"
    },
    {
        "name": "Isaac Thomas",
        "URL": "https://en.wikipedia.org/wiki/Isaac_Thomas",
        "party": "Democratic-Republican",
        "type": "Representative",
        "state": "Tennessee",
        "birth_date": "November 4, 1784",
        "death_date": "February 2, 1859",
        "age_at_congress": 30,
        "age_at_death": 74,
        "sex": "male"
    },
    {
        "name": "Bennett H. Henderson",
        "URL": "https://en.wikipedia.org/wiki/Bennett_H._Henderson",
        "party": "Democratic-Republican",
        "type": "Representative",
        "state": "Tennessee",
        "birth_date": "February 23, 1782",
        "death_date": "October 12, 1849",
        "age_at_congress": 33,
        "age_at_death": 67,
        "sex": "male"
    },
    {
        "name": "Newton Cannon",
        "URL": "https://en.wikipedia.org/wiki/Newton_Cannon",
        "party": "Democratic-Republican",
        "type": "Representative",
        "state": "Tennessee",
        "birth_date": "May 22, 1781",
        "death_date": "September 16, 1841",
        "age_at_congress": 33,
        "age_at_death": 60,
        "sex": "male"
    },
    {
        "name": "James B. Reynolds",
        "URL": "https://en.wikipedia.org/wiki/James_B._Reynolds",
        "party": "Democratic-Republican",
        "type": "Representative",
        "state": "Tennessee",
        "birth_date": "January 1, 1779",
        "death_date": "June 10, 1851",
        "age_at_congress": 36,
        "age_at_death": 72,
        "sex": "male"
    },
    {
        "name": "Daniel Chipman",
        "URL": "https://en.wikipedia.org/wiki/Daniel_Chipman",
        "party": "Federalist",
        "type": "Representative",
        "state": "Vermont",
        "birth_date": "October 22, 1765",
        "death_date": "April 23, 1850",
        "age_at_congress": 49,
        "age_at_death": 84,
        "sex": "male"
    },
    {
        "name": "Luther Jewett",
        "URL": "https://en.wikipedia.org/wiki/Luther_Jewett",
        "party": "Federalist",
        "type": "Representative",
        "state": "Vermont",
        "birth_date": "December 24, 1772",
        "death_date": "March 8, 1860",
        "age_at_congress": 42,
        "age_at_death": 87,
        "sex": "male"
    },
    {
        "name": "Chauncey Langdon",
        "URL": "https://en.wikipedia.org/wiki/Chauncey_Langdon",
        "party": "Federalist",
        "type": "Representative",
        "state": "Vermont",
        "birth_date": "November 8, 1763",
        "death_date": "July 23, 1830",
        "age_at_congress": 51,
        "age_at_death": 66,
        "sex": "male"
    },
    {
        "name": "Asa Lyon",
        "URL": "https://en.wikipedia.org/wiki/Asa_Lyon",
        "party": "Federalist",
        "type": "Representative",
        "state": "Vermont",
        "birth_date": "December 31, 1763",
        "death_date": "April 4, 1841",
        "age_at_congress": 51,
        "age_at_death": 77,
        "sex": "male"
    },
    {
        "name": "Charles Marsh",
        "URL": "https://en.wikipedia.org/wiki/Charles_Marsh_(American_politician)",
        "party": "Federalist",
        "type": "Representative",
        "state": "Vermont",
        "birth_date": "July 10, 1765",
        "death_date": "January 11, 1849",
        "age_at_congress": 49,
        "age_at_death": 83,
        "sex": "male"
    },
    {
        "name": "John Noyes",
        "URL": "https://en.wikipedia.org/wiki/John_Noyes_(politician)",
        "party": "Federalist",
        "type": "Representative",
        "state": "Vermont",
        "birth_date": "April 2, 1764",
        "death_date": "October 26, 1841",
        "age_at_congress": 50,
        "age_at_death": 77,
        "sex": "male"
    },
    {
        "name": "John G. Jackson",
        "URL": "https://en.wikipedia.org/wiki/John_G._Jackson_(politician)",
        "party": "Democratic-Republican",
        "type": "Representative",
        "state": "Virginia",
        "birth_date": "September 22, 1777",
        "death_date": "March 28, 1825",
        "age_at_congress": 37,
        "age_at_death": 47,
        "sex": "male"
    },
    {
        "name": "Magnus Tate",
        "URL": "https://en.wikipedia.org/wiki/Magnus_Tate",
        "party": "Federalist",
        "type": "Representative",
        "state": "Virginia",
        "birth_date": "September 1, 1767",
        "death_date": "March 30, 1823",
        "age_at_congress": 47,
        "age_at_death": 55,
        "sex": "male"
    },
    {
        "name": "Henry St. George Tucker",
        "URL": "https://en.wikipedia.org/wiki/Henry_St._George_Tucker_Sr.",
        "party": "Democratic-Republican",
        "type": "Representative",
        "state": "Virginia",
        "birth_date": "December 29, 1780",
        "death_date": "August 28, 1848",
        "age_at_congress": 34,
        "age_at_death": 67,
        "sex": "male"
    },
    {
        "name": "William McCoy",
        "URL": "https://en.wikipedia.org/wiki/William_McCoy_(congressman)",
        "party": "Democratic-Republican",
        "type": "Representative",
        "state": "Virginia",
        "birth_date": "September 20, 1768",
        "death_date": "August 19, 1835",
        "age_at_congress": 46,
        "age_at_death": 66,
        "sex": "male"
    },
    {
        "name": "James Breckinridge",
        "URL": "https://en.wikipedia.org/wiki/James_Breckinridge",
        "party": "Federalist",
        "type": "Representative",
        "state": "Virginia",
        "birth_date": "March 7, 1763",
        "death_date": "May 13, 1833",
        "age_at_congress": 52,
        "age_at_death": 70,
        "sex": "male"
    },
    {
        "name": "Daniel Sheffey",
        "URL": "https://en.wikipedia.org/wiki/Daniel_Sheffey",
        "party": "Federalist",
        "type": "Representative",
        "state": "Virginia",
        "birth_date": "January 1, 1770",
        "death_date": "December 3, 1830",
        "age_at_congress": 45,
        "age_at_death": 60,
        "sex": "male"
    },
    {
        "name": "Ballard Smith",
        "URL": "https://en.wikipedia.org/wiki/Ballard_Smith_(Virginia_politician)",
        "party": "Democratic-Republican",
        "type": "Representative",
        "state": "Virginia",
        "birth_date": null,
        "death_date": null,
        "age_at_congress": null,
        "age_at_death": null,
        "sex": "male"
    },
    {
        "name": "Joseph Lewis Jr.",
        "URL": "https://en.wikipedia.org/wiki/Joseph_Lewis_Jr._(Virginia_politician)",
        "party": "Federalist",
        "type": "Representative",
        "state": "Virginia",
        "birth_date": "January 1, 1772",
        "death_date": "March 30, 1834",
        "age_at_congress": 43,
        "age_at_death": 62,
        "sex": "male"
    },
    {
        "name": "John P. Hungerford",
        "URL": "https://en.wikipedia.org/wiki/John_Hungerford_(congressman)",
        "party": "Democratic-Republican",
        "type": "Representative",
        "state": "Virginia",
        "birth_date": "January 2, 1761",
        "death_date": "December 21, 1833",
        "age_at_congress": 54,
        "age_at_death": 73,
        "sex": "male"
    },
    {
        "name": "Aylett Hawes",
        "URL": "https://en.wikipedia.org/wiki/Aylett_Hawes",
        "party": "Democratic-Republican",
        "type": "Representative",
        "state": "Virginia",
        "birth_date": "April 21, 1768",
        "death_date": "August 31, 1833",
        "age_at_congress": 46,
        "age_at_death": 65,
        "sex": "male"
    },
    {
        "name": "Philip P. Barbour",
        "URL": "https://en.wikipedia.org/wiki/Philip_P._Barbour",
        "party": "Democratic-Republican",
        "type": "Representative",
        "state": "Virginia",
        "birth_date": "May 25, 1783",
        "death_date": "February 25, 1841",
        "age_at_congress": 31,
        "age_at_death": 57,
        "sex": "male"
    },
    {
        "name": "William H. Roane",
        "URL": "https://en.wikipedia.org/wiki/William_H._Roane",
        "party": "Democratic-Republican",
        "type": "Representative",
        "state": "Virginia",
        "birth_date": "September 17, 1787",
        "death_date": "May 11, 1845",
        "age_at_congress": 27,
        "age_at_death": 57,
        "sex": "male"
    },
    {
        "name": "Burwell Bassett",
        "URL": "https://en.wikipedia.org/wiki/Burwell_Bassett",
        "party": "Democratic-Republican",
        "type": "Representative",
        "state": "Virginia",
        "birth_date": "March 18, 1764",
        "death_date": "February 26, 1841",
        "age_at_congress": 50,
        "age_at_death": 76,
        "sex": "male"
    },
    {
        "name": "William A. Burwell",
        "URL": "https://en.wikipedia.org/wiki/William_A._Burwell",
        "party": "Democratic-Republican",
        "type": "Representative",
        "state": "Virginia",
        "birth_date": "March 15, 1780",
        "death_date": "February 16, 1821",
        "age_at_congress": 34,
        "age_at_death": 40,
        "sex": "male"
    },
    {
        "name": "Matthew Clay",
        "URL": "https://en.wikipedia.org/wiki/Matthew_Clay",
        "party": "Democratic-Republican",
        "type": "Representative",
        "state": "Virginia",
        "birth_date": "March 25, 1754",
        "death_date": "May 27, 1815",
        "age_at_congress": 60,
        "age_at_death": 61,
        "sex": "male"
    },
    {
        "name": "John Randolph",
        "URL": "https://en.wikipedia.org/wiki/John_Randolph_of_Roanoke",
        "party": "Democratic-Republican",
        "type": "Representative",
        "state": "Virginia",
        "birth_date": "June 2, 1773",
        "death_date": "May 24, 1833",
        "age_at_congress": 41,
        "age_at_death": 60,
        "sex": "male"
    },
    {
        "name": "James Pleasants",
        "URL": "https://en.wikipedia.org/wiki/James_Pleasants",
        "party": "Democratic-Republican",
        "type": "Representative",
        "state": "Virginia",
        "birth_date": "October 24, 1769",
        "death_date": "November 9, 1836",
        "age_at_congress": 45,
        "age_at_death": 67,
        "sex": "male"
    },
    {
        "name": "Thomas Gholson Jr.",
        "URL": "https://en.wikipedia.org/wiki/Thomas_Gholson_Jr.",
        "party": "Democratic-Republican",
        "type": "Representative",
        "state": "Virginia",
        "birth_date": "January 1, 1780",
        "death_date": "July 14, 1816",
        "age_at_congress": 35,
        "age_at_death": 36,
        "sex": "male"
    },
    {
        "name": "Peterson Goodwyn",
        "URL": "https://en.wikipedia.org/wiki/Peterson_Goodwyn",
        "party": "Democratic-Republican",
        "type": "Representative",
        "state": "Virginia",
        "birth_date": "January 1, 1745",
        "death_date": "February 21, 1818",
        "age_at_congress": 70,
        "age_at_death": 73,
        "sex": "male"
    },
    {
        "name": "James Johnson",
        "URL": "https://en.wikipedia.org/wiki/James_Johnson_(VA_congressman)",
        "party": "Democratic-Republican",
        "type": "Representative",
        "state": "Virginia",
        "birth_date": null,
        "death_date": "December 7, 1825",
        "age_at_congress": null,
        "age_at_death": null,
        "sex": "male"
    },
    {
        "name": "Thomas Newton Jr.",
        "URL": "https://en.wikipedia.org/wiki/Thomas_Newton_Jr.",
        "party": "Democratic-Republican",
        "type": "Representative",
        "state": "Virginia",
        "birth_date": "November 21, 1768",
        "death_date": "August 5, 1847",
        "age_at_congress": 46,
        "age_at_death": 78,
        "sex": "male"
    },
    {
        "name": "Hugh Nelson",
        "URL": "https://en.wikipedia.org/wiki/Hugh_Nelson_(congressman)",
        "party": "Democratic-Republican",
        "type": "Representative",
        "state": "Virginia",
        "birth_date": "September 30, 1768",
        "death_date": "March 18, 1836",
        "age_at_congress": 46,
        "age_at_death": 67,
        "sex": "male"
    },
    {
        "name": "John Clopton",
        "URL": "https://en.wikipedia.org/wiki/John_Clopton",
        "party": "Democratic-Republican",
        "type": "Representative",
        "state": "Virginia",
        "birth_date": "February 7, 1756",
        "death_date": "September 11, 1816",
        "age_at_congress": 59,
        "age_at_death": 60,
        "sex": "male"
    }
]